wsgirouter3.py
wsgirouter3-0.8.4.dist-info/LICENSE
wsgirouter3-0.8.4.dist-info/METADATA
wsgirouter3-0.8.4.dist-info/WHEEL
wsgirouter3-0.8.4.dist-info/top_level.txt
wsgirouter3-0.8.4.dist-info/RECORD
